scratchcon/__init__.py
scratchcon/common.py
scratchcon/conn.py
scratchcon/exceptions.py
scratchcon/project.py
scratchcon/studio.py
scratchcon/user.py
scratchcon/actions/__init__.py
scratchcon/actions/actions.py
scratchcon/actions/common.py
scratchcon/actions/conn.py
scratchcon/actions/login.py
scratchcon/utils/__init__.py
scratchcon/utils/auth.py
scratchcon/utils/filterbot.py
scratchcon-1.3.5b0.dist-info/LICENSE
scratchcon-1.3.5b0.dist-info/METADATA
scratchcon-1.3.5b0.dist-info/WHEEL
scratchcon-1.3.5b0.dist-info/top_level.txt
scratchcon-1.3.5b0.dist-info/RECORD
