Metadata-Version: 2.1
Name: scratchcon
Version: 1.3.5b0
Summary: https://github.com/g1ad05/scratchcon
Author-email: -G1ad05- <on67703@gmail.com>, webbrowser11 <terpstragraham@gmail.com>
Requires-Python: >=3.9
License-File: LICENSE
Requires-Dist: requests
Requires-Dist: scratchattach
Requires-Dist: pyperclip
Requires-Dist: colorama
